<PAMDataset>
  <Metadata>
    <MDI key="DataType">Generic</MDI>
  </Metadata>
  <PAMRasterBand band="1">
    <Histograms>
      <HistItem>
        <HistMin>-0.5</HistMin>
        <HistMax>234.5</HistMax>
        <BucketCount>235</BucketCount>
        <IncludeOutOfRange>1</IncludeOutOfRange>
        <Approximate>0</Approximate>
        <HistCounts>0|0|0|0|0|0|0|0|0|0|0|0|0|0|0|0|0|0|0|0|0|0|0|0|0|0|0|0|0|0|0|0|0|0|0|0|0|0|0|0|0|0|0|0|0|0|0|0|0|0|0|0|0|0|0|0|0|0|0|1|1|2|2|1|1|5|4|1|1|4|10|10|12|8|13|14|10|19|26|34|30|36|47|66|62|76|78|87|81|97|86|103|100|132|121|137|163|175|172|219|223|219|254|281|282|307|328|335|388|397|412|497|502|538|561|550|613|649|670|645|674|746|798|769|797|815|912|902|924|958|1063|1086|1168|1156|1165|1231|1265|1287|1384|1427|1426|1490|1586|1598|1613|1631|1709|1753|1715|1765|1852|1911|1937|1865|2028|2024|2188|2129|2072|2080|2165|2252|2213|2284|2223|2092|2157|2255|2156|2148|2250|2229|2282|2206|2090|2151|2160|2017|2026|2004|1959|2002|1819|1672|1679|1514|1479|1347|1321|1273|1113|1088|975|850|852|792|706|689|641|643|572|477|441|445|404|336|329|287|267|247|218|203|209|137|103|115|91|91|83|62|67|56|45|48|31|22|16|8|10|2|4|1|0|1|1</HistCounts>
      </HistItem>
    </Histograms>
    <Metadata>
      <MDI key="RepresentationType">ATHEMATIC</MDI>
      <MDI key="STATISTICS_COVARIANCES">644.3657738901611,563.1653186373875,503.3557569237807,0</MDI>
      <MDI key="STATISTICS_EXCLUDEDVALUES"></MDI>
      <MDI key="STATISTICS_MAXIMUM">234</MDI>
      <MDI key="STATISTICS_MEAN">158.56956028369</MDI>
      <MDI key="STATISTICS_MINIMUM">59</MDI>
      <MDI key="STATISTICS_SKIPFACTORX">1</MDI>
      <MDI key="STATISTICS_SKIPFACTORY">1</MDI>
      <MDI key="STATISTICS_STDDEV">25.38436081311</MDI>
    </Metadata>
  </PAMRasterBand>
  <PAMRasterBand band="2">
    <Histograms>
      <HistItem>
        <HistMin>-0.5</HistMin>
        <HistMax>212.5</HistMax>
        <BucketCount>213</BucketCount>
        <IncludeOutOfRange>1</IncludeOutOfRange>
        <Approximate>0</Approximate>
        <HistCounts>0|0|0|0|0|0|0|0|0|0|0|0|0|0|0|0|0|0|0|0|0|0|0|0|0|0|0|0|0|0|0|0|0|0|0|0|0|0|0|0|0|0|0|0|0|0|0|0|0|0|0|0|0|0|0|0|0|0|0|1|2|0|2|0|3|12|7|14|13|14|15|22|22|31|35|37|26|37|54|56|61|73|83|90|86|106|116|136|123|135|151|188|188|214|213|219|229|239|284|284|321|368|383|405|424|423|488|485|571|572|583|665|637|690|722|774|792|797|813|876|909|964|978|1001|1008|1101|1069|1139|1158|1181|1259|1248|1370|1389|1457|1486|1485|1630|1599|1715|1715|1787|1821|1923|1894|1976|2037|2024|2073|2071|2036|2239|2236|2325|2227|2300|2286|2390|2317|2409|2396|2455|2544|2404|2423|2432|2391|2398|2370|2317|2412|2276|2277|2096|2089|1984|1813|1775|1675|1548|1480|1370|1287|1251|1081|992|936|860|705|662|557|501|417|384|310|244|241|186|156|120|129|90|75|66|48|31|32|21|22|12|7|4|6</HistCounts>
      </HistItem>
    </Histograms>
    <Metadata>
      <MDI key="RepresentationType">ATHEMATIC</MDI>
      <MDI key="STATISTICS_COVARIANCES">563.1653186373875,563.5626879049823,436.3900460136085,0</MDI>
      <MDI key="STATISTICS_EXCLUDEDVALUES"></MDI>
      <MDI key="STATISTICS_MAXIMUM">212</MDI>
      <MDI key="STATISTICS_MEAN">151.34617021277</MDI>
      <MDI key="STATISTICS_MINIMUM">59</MDI>
      <MDI key="STATISTICS_SKIPFACTORX">1</MDI>
      <MDI key="STATISTICS_SKIPFACTORY">1</MDI>
      <MDI key="STATISTICS_STDDEV">23.739475308123</MDI>
    </Metadata>
  </PAMRasterBand>
  <PAMRasterBand band="3">
    <Histograms>
      <HistItem>
        <HistMin>-0.5</HistMin>
        <HistMax>190.5</HistMax>
        <BucketCount>191</BucketCount>
        <IncludeOutOfRange>1</IncludeOutOfRange>
        <Approximate>0</Approximate>
        <HistCounts>0|0|0|0|0|0|0|0|0|0|0|0|0|0|0|0|0|0|0|0|0|0|0|0|0|0|0|0|0|0|0|0|0|0|0|0|0|0|0|0|0|0|0|1|2|5|8|3|5|14|11|17|24|27|28|39|38|49|51|61|83|89|115|134|140|179|221|227|242|293|337|355|380|392|456|486|505|513|621|632|658|685|733|769|864|976|998|990|1104|1101|1192|1279|1307|1224|1414|1439|1556|1568|1684|1683|1792|1860|1818|1997|2007|2105|2098|2277|2294|2320|2343|2463|2500|2567|2629|2618|2727|2762|2740|2842|2785|2826|2885|2799|2682|2658|2616|2616|2561|2403|2410|2343|2101|2169|1928|1939|1834|1707|1690|1487|1492|1281|1273|1203|1125|1039|975|889|812|750|783|705|590|550|496|417|384|381|300|274|246|209|206|191|164|154|153|120|88|78|67|76|57|39|39|43|27|18|31|18|13|14|12|1|2|4|0|2|1|2|1</HistCounts>
      </HistItem>
    </Histograms>
    <Metadata>
      <MDI key="RepresentationType">ATHEMATIC</MDI>
      <MDI key="STATISTICS_COVARIANCES">503.3557569237807,436.3900460136085,434.3768706171112,0</MDI>
      <MDI key="STATISTICS_EXCLUDEDVALUES"></MDI>
      <MDI key="STATISTICS_MAXIMUM">190</MDI>
      <MDI key="STATISTICS_MEAN">116.15758865248</MDI>
      <MDI key="STATISTICS_MINIMUM">43</MDI>
      <MDI key="STATISTICS_SKIPFACTORX">1</MDI>
      <MDI key="STATISTICS_SKIPFACTORY">1</MDI>
      <MDI key="STATISTICS_STDDEV">20.841709877482</MDI>
    </Metadata>
  </PAMRasterBand>
  <PAMRasterBand band="4">
    <Histograms>
      <HistItem>
        <HistMin>-0.5</HistMin>
        <HistMax>255.5</HistMax>
        <BucketCount>256</BucketCount>
        <IncludeOutOfRange>1</IncludeOutOfRange>
        <Approximate>0</Approximate>
        <HistCounts>0|0|0|0|0|0|0|0|0|0|0|0|0|0|0|0|0|0|0|0|0|0|0|0|0|0|0|0|0|0|0|0|0|0|0|0|0|0|0|0|0|0|0|0|0|0|0|0|0|0|0|0|0|0|0|0|0|0|0|0|0|0|0|0|0|0|0|0|0|0|0|0|0|0|0|0|0|0|0|0|0|0|0|0|0|0|0|0|0|0|0|0|0|0|0|0|0|0|0|0|0|0|0|0|0|0|0|0|0|0|0|0|0|0|0|0|0|0|0|0|0|0|0|0|0|0|0|0|0|0|0|0|0|0|0|0|0|0|0|0|0|0|0|0|0|0|0|0|0|0|0|0|0|0|0|0|0|0|0|0|0|0|0|0|0|0|0|0|0|0|0|0|0|0|0|0|0|0|0|0|0|0|0|0|0|0|0|0|0|0|0|0|0|0|0|0|0|0|0|0|0|0|0|0|0|0|0|0|0|0|0|0|0|0|0|0|0|0|0|0|0|0|0|0|0|0|0|0|0|0|0|0|0|0|0|0|0|0|0|0|0|0|0|0|0|0|0|0|0|0|0|0|0|0|0|141000</HistCounts>
      </HistItem>
    </Histograms>
    <Metadata>
      <MDI key="RepresentationType">ATHEMATIC</MDI>
      <MDI key="STATISTICS_COVARIANCES">0,0,0,0</MDI>
      <MDI key="STATISTICS_EXCLUDEDVALUES"></MDI>
      <MDI key="STATISTICS_MAXIMUM">255</MDI>
      <MDI key="STATISTICS_MEAN">255</MDI>
      <MDI key="STATISTICS_MINIMUM">255</MDI>
      <MDI key="STATISTICS_SKIPFACTORX">1</MDI>
      <MDI key="STATISTICS_SKIPFACTORY">1</MDI>
      <MDI key="STATISTICS_STDDEV">0</MDI>
    </Metadata>
  </PAMRasterBand>
</PAMDataset>
