<PAMDataset>
  <Metadata>
    <MDI key="DataType">Generic</MDI>
  </Metadata>
  <PAMRasterBand band="1">
    <Histograms>
      <HistItem>
        <HistMin>-0.5</HistMin>
        <HistMax>254.5</HistMax>
        <BucketCount>255</BucketCount>
        <IncludeOutOfRange>1</IncludeOutOfRange>
        <Approximate>0</Approximate>
        <HistCounts>0|0|0|0|0|0|0|0|0|0|0|0|0|0|0|0|0|0|0|0|0|0|0|0|0|0|0|0|0|0|0|0|0|0|0|0|0|0|0|0|0|0|0|0|0|0|0|0|0|0|0|0|0|0|0|0|0|0|0|0|0|0|0|0|0|0|0|0|0|0|0|0|0|0|0|0|0|0|0|0|0|0|0|0|0|0|0|0|0|0|0|0|0|0|0|0|0|0|0|0|0|0|0|0|0|0|0|0|0|0|0|0|0|0|0|0|0|0|0|0|0|0|0|0|0|0|0|0|0|0|0|0|0|0|0|0|0|0|1|2|0|6|2|4|4|3|4|4|9|9|7|11|18|25|25|36|37|55|49|61|75|87|115|121|144|163|192|215|290|297|390|457|525|596|626|723|821|833|1034|1076|1133|1175|1227|1303|1510|1465|1595|1614|1741|1897|2044|2129|2223|2348|2459|2556|2550|2779|2875|2828|3010|3005|3083|3178|3392|3306|3363|3537|3465|3351|3204|3189|3058|3119|3083|2972|2870|2811|2718|2557|2621|2353|2229|2068|1942|1787|1731|1672|1469|1381|1233|1202|1056|972|915|771|742|629|562|503|443|383|332|270|183|117|98|46|19|3|6|4|2|5|2</HistCounts>
      </HistItem>
    </Histograms>
    <Metadata>
      <MDI key="RepresentationType">ATHEMATIC</MDI>
      <MDI key="STATISTICS_COVARIANCES">273.7363650379223,256.3111224546361,248.1409829562688,0</MDI>
      <MDI key="STATISTICS_EXCLUDEDVALUES"></MDI>
      <MDI key="STATISTICS_MAXIMUM">254</MDI>
      <MDI key="STATISTICS_MEAN">205.74468977778</MDI>
      <MDI key="STATISTICS_MINIMUM">138</MDI>
      <MDI key="STATISTICS_SKIPFACTORX">1</MDI>
      <MDI key="STATISTICS_SKIPFACTORY">1</MDI>
      <MDI key="STATISTICS_STDDEV">16.544980055531</MDI>
    </Metadata>
  </PAMRasterBand>
  <PAMRasterBand band="2">
    <Histograms>
      <HistItem>
        <HistMin>-0.5</HistMin>
        <HistMax>236.5</HistMax>
        <BucketCount>237</BucketCount>
        <IncludeOutOfRange>1</IncludeOutOfRange>
        <Approximate>0</Approximate>
        <HistCounts>0|0|0|0|0|0|0|0|0|0|0|0|0|0|0|0|0|0|0|0|0|0|0|0|0|0|0|0|0|0|0|0|0|0|0|0|0|0|0|0|0|0|0|0|0|0|0|0|0|0|0|0|0|0|0|0|0|0|0|0|0|0|0|0|0|0|0|0|0|0|0|0|0|0|0|0|0|0|0|0|0|0|0|0|0|0|0|0|0|0|0|0|0|0|0|0|0|0|0|0|0|0|0|0|0|0|0|0|0|0|0|0|1|2|1|2|2|4|4|2|5|7|11|15|18|21|24|31|35|44|54|70|74|113|107|134|169|199|227|323|339|384|446|568|586|721|817|875|962|1016|1147|1178|1197|1377|1421|1600|1579|1710|1777|1866|1999|2095|2370|2467|2543|2599|2728|2772|2985|3006|3232|3223|3361|3518|3682|3497|3688|3661|3590|3664|3641|3485|3364|3196|3098|3118|3001|2923|2731|2552|2412|2196|2106|1891|1881|1619|1500|1361|1309|1155|1141|950|862|769|709|607|501|436|332|337|245|214|205|173|134|104|93|62|53|43|35|33|19|14|21|12|9|6|6|7|3|0|1|0|1|2|2</HistCounts>
      </HistItem>
    </Histograms>
    <Metadata>
      <MDI key="RepresentationType">ATHEMATIC</MDI>
      <MDI key="STATISTICS_COVARIANCES">256.3111224546361,248.0145828283319,236.2207354590206,0</MDI>
      <MDI key="STATISTICS_EXCLUDEDVALUES"></MDI>
      <MDI key="STATISTICS_MAXIMUM">236</MDI>
      <MDI key="STATISTICS_MEAN">175.18049422222</MDI>
      <MDI key="STATISTICS_MINIMUM">112</MDI>
      <MDI key="STATISTICS_SKIPFACTORX">1</MDI>
      <MDI key="STATISTICS_SKIPFACTORY">1</MDI>
      <MDI key="STATISTICS_STDDEV">15.74847874648</MDI>
    </Metadata>
  </PAMRasterBand>
  <PAMRasterBand band="3">
    <Histograms>
      <HistItem>
        <HistMin>-0.5</HistMin>
        <HistMax>213.5</HistMax>
        <BucketCount>214</BucketCount>
        <IncludeOutOfRange>1</IncludeOutOfRange>
        <Approximate>0</Approximate>
        <HistCounts>0|0|0|0|0|0|0|0|0|0|0|0|0|0|0|0|0|0|0|0|0|0|0|0|0|0|0|0|0|0|0|0|0|0|0|0|0|0|0|0|0|0|0|0|0|0|0|0|0|0|0|0|0|0|0|0|0|0|0|0|0|0|0|0|0|0|0|0|0|0|0|0|0|0|0|0|0|0|0|0|0|0|0|0|0|0|0|2|1|3|2|4|3|5|5|10|6|15|16|30|34|41|48|48|87|77|104|118|147|199|236|298|307|360|423|528|585|736|718|909|998|1091|1198|1225|1422|1547|1636|1701|1808|1905|1957|2185|2351|2456|2671|2722|2883|3012|3119|3255|3244|3414|3502|3535|3652|3686|3669|3703|3653|3621|3425|3474|3301|3252|3094|3118|2921|2876|2760|2660|2499|2319|2125|1982|1772|1709|1578|1426|1304|1192|1102|958|958|828|752|705|541|523|443|347|344|253|225|188|141|119|109|82|56|53|41|26|28|18|16|14|10|8|5|4|4|2|3|0|1|2|0|0|1|0|1|0|0|1</HistCounts>
      </HistItem>
    </Histograms>
    <Metadata>
      <MDI key="RepresentationType">ATHEMATIC</MDI>
      <MDI key="STATISTICS_COVARIANCES">248.1409829562688,236.2207354590206,234.6411624275739,0</MDI>
      <MDI key="STATISTICS_EXCLUDEDVALUES"></MDI>
      <MDI key="STATISTICS_MAXIMUM">213</MDI>
      <MDI key="STATISTICS_MEAN">145.95592533333</MDI>
      <MDI key="STATISTICS_MINIMUM">87</MDI>
      <MDI key="STATISTICS_SKIPFACTORX">1</MDI>
      <MDI key="STATISTICS_SKIPFACTORY">1</MDI>
      <MDI key="STATISTICS_STDDEV">15.318001254327</MDI>
    </Metadata>
  </PAMRasterBand>
  <PAMRasterBand band="4">
    <Histograms>
      <HistItem>
        <HistMin>-0.5</HistMin>
        <HistMax>255.5</HistMax>
        <BucketCount>256</BucketCount>
        <IncludeOutOfRange>1</IncludeOutOfRange>
        <Approximate>0</Approximate>
        <HistCounts>0|0|0|0|0|0|0|0|0|0|0|0|0|0|0|0|0|0|0|0|0|0|0|0|0|0|0|0|0|0|0|0|0|0|0|0|0|0|0|0|0|0|0|0|0|0|0|0|0|0|0|0|0|0|0|0|0|0|0|0|0|0|0|0|0|0|0|0|0|0|0|0|0|0|0|0|0|0|0|0|0|0|0|0|0|0|0|0|0|0|0|0|0|0|0|0|0|0|0|0|0|0|0|0|0|0|0|0|0|0|0|0|0|0|0|0|0|0|0|0|0|0|0|0|0|0|0|0|0|0|0|0|0|0|0|0|0|0|0|0|0|0|0|0|0|0|0|0|0|0|0|0|0|0|0|0|0|0|0|0|0|0|0|0|0|0|0|0|0|0|0|0|0|0|0|0|0|0|0|0|0|0|0|0|0|0|0|0|0|0|0|0|0|0|0|0|0|0|0|0|0|0|0|0|0|0|0|0|0|0|0|0|0|0|0|0|0|0|0|0|0|0|0|0|0|0|0|0|0|0|0|0|0|0|0|0|0|0|0|0|0|0|0|0|0|0|0|0|0|0|0|0|0|0|0|140625</HistCounts>
      </HistItem>
    </Histograms>
    <Metadata>
      <MDI key="RepresentationType">ATHEMATIC</MDI>
      <MDI key="STATISTICS_COVARIANCES">0,0,0,0</MDI>
      <MDI key="STATISTICS_EXCLUDEDVALUES"></MDI>
      <MDI key="STATISTICS_MAXIMUM">255</MDI>
      <MDI key="STATISTICS_MEAN">255</MDI>
      <MDI key="STATISTICS_MINIMUM">255</MDI>
      <MDI key="STATISTICS_SKIPFACTORX">1</MDI>
      <MDI key="STATISTICS_SKIPFACTORY">1</MDI>
      <MDI key="STATISTICS_STDDEV">0</MDI>
    </Metadata>
  </PAMRasterBand>
</PAMDataset>
