<PAMDataset>
  <Metadata>
    <MDI key="DataType">Generic</MDI>
  </Metadata>
  <PAMRasterBand band="1">
    <Histograms>
      <HistItem>
        <HistMin>-0.5</HistMin>
        <HistMax>218.5</HistMax>
        <BucketCount>219</BucketCount>
        <IncludeOutOfRange>1</IncludeOutOfRange>
        <Approximate>0</Approximate>
        <HistCounts>0|0|0|0|0|0|0|0|0|0|0|0|0|0|0|0|0|0|0|0|0|0|0|0|0|0|0|0|0|0|0|0|0|0|0|0|0|0|0|0|0|0|0|0|0|0|0|0|0|0|0|1|1|2|3|2|1|4|9|4|13|9|9|11|9|9|15|16|25|28|35|44|48|53|60|80|69|90|98|113|147|156|186|187|215|215|272|284|312|308|403|361|431|475|548|499|587|570|626|737|754|810|823|918|973|1003|1073|1130|1198|1222|1330|1402|1474|1452|1554|1659|1684|1791|1788|1971|1938|2086|2107|2167|2282|2235|2319|2373|2497|2527|2476|2593|2555|2570|2610|2585|2696|2570|2632|2568|2505|2492|2567|2471|2490|2280|2271|2282|2267|2239|2197|2047|1962|1796|1866|1712|1692|1563|1470|1413|1318|1250|1154|1110|1084|1011|895|829|762|759|738|627|578|471|464|434|390|323|307|258|228|205|168|157|121|125|82|63|71|43|51|30|28|24|26|21|15|4|8|7|7|0|3|1|0|2|0|1|1|1|1|1|3|3|1|1|1|1|1</HistCounts>
      </HistItem>
    </Histograms>
    <Metadata>
      <MDI key="RepresentationType">ATHEMATIC</MDI>
      <MDI key="STATISTICS_COVARIANCES">454.8548951681552,449.0335788200877,388.6689527693428,0</MDI>
      <MDI key="STATISTICS_EXCLUDEDVALUES"></MDI>
      <MDI key="STATISTICS_MAXIMUM">218</MDI>
      <MDI key="STATISTICS_MEAN">134.05794844444</MDI>
      <MDI key="STATISTICS_MINIMUM">51</MDI>
      <MDI key="STATISTICS_SKIPFACTORX">1</MDI>
      <MDI key="STATISTICS_SKIPFACTORY">1</MDI>
      <MDI key="STATISTICS_STDDEV">21.327327426758</MDI>
    </Metadata>
  </PAMRasterBand>
  <PAMRasterBand band="2">
    <Histograms>
      <HistItem>
        <HistMin>-0.5</HistMin>
        <HistMax>219.5</HistMax>
        <BucketCount>220</BucketCount>
        <IncludeOutOfRange>1</IncludeOutOfRange>
        <Approximate>0</Approximate>
        <HistCounts>0|0|0|0|0|0|0|0|0|0|0|0|0|0|0|0|0|0|0|0|0|0|0|0|0|0|0|0|0|0|0|0|0|0|0|0|0|0|0|0|0|0|0|0|0|0|0|0|0|0|0|0|0|0|1|2|0|0|1|1|2|0|2|2|4|1|4|7|6|4|9|8|14|12|14|21|15|21|23|38|43|49|51|47|49|74|62|87|100|110|140|150|133|168|156|222|229|254|253|280|311|326|406|413|392|489|494|525|574|574|662|718|696|756|821|822|914|960|1040|1118|1098|1197|1302|1336|1405|1470|1524|1585|1705|1754|1774|1846|1947|1976|1999|2175|2178|2210|2364|2394|2359|2430|2459|2515|2560|2557|2679|2728|2592|2656|2589|2612|2633|2516|2651|2516|2483|2530|2433|2335|2187|2214|2205|2035|2063|1960|1877|1791|1694|1651|1540|1389|1434|1342|1167|1136|1026|981|880|828|836|751|687|591|511|525|480|414|354|339|261|245|229|177|159|127|116|102|66|73|55|43|22|16|22|15|9|10|10|5|6|4|4|0|1|1|2|3|0|2</HistCounts>
      </HistItem>
    </Histograms>
    <Metadata>
      <MDI key="RepresentationType">ATHEMATIC</MDI>
      <MDI key="STATISTICS_COVARIANCES">449.0335788200877,456.2490160531959,385.9436282752885,0</MDI>
      <MDI key="STATISTICS_EXCLUDEDVALUES"></MDI>
      <MDI key="STATISTICS_MAXIMUM">219</MDI>
      <MDI key="STATISTICS_MEAN">146.10124088889</MDI>
      <MDI key="STATISTICS_MINIMUM">54</MDI>
      <MDI key="STATISTICS_SKIPFACTORX">1</MDI>
      <MDI key="STATISTICS_SKIPFACTORY">1</MDI>
      <MDI key="STATISTICS_STDDEV">21.359986330829</MDI>
    </Metadata>
  </PAMRasterBand>
  <PAMRasterBand band="3">
    <Histograms>
      <HistItem>
        <HistMin>-0.5</HistMin>
        <HistMax>196.5</HistMax>
        <BucketCount>197</BucketCount>
        <IncludeOutOfRange>1</IncludeOutOfRange>
        <Approximate>0</Approximate>
        <HistCounts>0|0|0|0|0|0|0|0|0|0|0|0|0|0|0|0|0|0|0|0|0|0|0|0|0|0|0|0|0|0|0|0|0|0|0|0|0|0|0|0|1|0|1|2|4|4|2|6|7|2|7|6|6|9|6|12|12|19|25|41|48|49|48|69|82|95|131|150|156|189|205|241|277|315|349|385|415|501|534|554|603|726|736|777|858|914|978|1098|1113|1193|1298|1423|1480|1529|1657|1747|1832|1820|1992|2009|2280|2257|2399|2474|2577|2563|2693|2751|2679|2871|2863|2966|2916|2930|2987|2945|3001|2916|2861|2887|2791|2804|2722|2679|2617|2477|2409|2416|2327|2131|2049|2051|1922|1763|1732|1642|1492|1443|1325|1294|1217|1125|1041|949|924|829|773|692|640|587|531|469|418|390|318|297|260|222|165|163|172|129|92|86|76|60|56|49|34|31|26|26|23|20|9|10|11|9|7|6|2|4|2|2|4|5|1|1|4|4|0|0|1|1|0|1|1</HistCounts>
      </HistItem>
    </Histograms>
    <Metadata>
      <MDI key="RepresentationType">ATHEMATIC</MDI>
      <MDI key="STATISTICS_COVARIANCES">388.6689527693428,385.9436282752885,358.46863854039,0</MDI>
      <MDI key="STATISTICS_EXCLUDEDVALUES"></MDI>
      <MDI key="STATISTICS_MAXIMUM">196</MDI>
      <MDI key="STATISTICS_MEAN">114.18348088889</MDI>
      <MDI key="STATISTICS_MINIMUM">40</MDI>
      <MDI key="STATISTICS_SKIPFACTORX">1</MDI>
      <MDI key="STATISTICS_SKIPFACTORY">1</MDI>
      <MDI key="STATISTICS_STDDEV">18.933268036459</MDI>
    </Metadata>
  </PAMRasterBand>
  <PAMRasterBand band="4">
    <Histograms>
      <HistItem>
        <HistMin>-0.5</HistMin>
        <HistMax>255.5</HistMax>
        <BucketCount>256</BucketCount>
        <IncludeOutOfRange>1</IncludeOutOfRange>
        <Approximate>0</Approximate>
        <HistCounts>0|0|0|0|0|0|0|0|0|0|0|0|0|0|0|0|0|0|0|0|0|0|0|0|0|0|0|0|0|0|0|0|0|0|0|0|0|0|0|0|0|0|0|0|0|0|0|0|0|0|0|0|0|0|0|0|0|0|0|0|0|0|0|0|0|0|0|0|0|0|0|0|0|0|0|0|0|0|0|0|0|0|0|0|0|0|0|0|0|0|0|0|0|0|0|0|0|0|0|0|0|0|0|0|0|0|0|0|0|0|0|0|0|0|0|0|0|0|0|0|0|0|0|0|0|0|0|0|0|0|0|0|0|0|0|0|0|0|0|0|0|0|0|0|0|0|0|0|0|0|0|0|0|0|0|0|0|0|0|0|0|0|0|0|0|0|0|0|0|0|0|0|0|0|0|0|0|0|0|0|0|0|0|0|0|0|0|0|0|0|0|0|0|0|0|0|0|0|0|0|0|0|0|0|0|0|0|0|0|0|0|0|0|0|0|0|0|0|0|0|0|0|0|0|0|0|0|0|0|0|0|0|0|0|0|0|0|0|0|0|0|0|0|0|0|0|0|0|0|0|0|0|0|0|0|140625</HistCounts>
      </HistItem>
    </Histograms>
    <Metadata>
      <MDI key="RepresentationType">ATHEMATIC</MDI>
      <MDI key="STATISTICS_COVARIANCES">0,0,0,0</MDI>
      <MDI key="STATISTICS_EXCLUDEDVALUES"></MDI>
      <MDI key="STATISTICS_MAXIMUM">255</MDI>
      <MDI key="STATISTICS_MEAN">255</MDI>
      <MDI key="STATISTICS_MINIMUM">255</MDI>
      <MDI key="STATISTICS_SKIPFACTORX">1</MDI>
      <MDI key="STATISTICS_SKIPFACTORY">1</MDI>
      <MDI key="STATISTICS_STDDEV">0</MDI>
    </Metadata>
  </PAMRasterBand>
</PAMDataset>
